<?xml version="1.0"?>
<AudioCatalog xmlns="http://cs.skuniv.ac.kr/xml/ldg"
		xmlns:xsi="http://www.w3.org/2001/XMLSchema-instance"
		xsi:schemaLocation="http://cs.skuniv.ac.kr/xml/ldg AudioCatalog.xsd">

	<Cd>
		<Title>BTD 1집</Title>
		<Artist>BTS</Artist>
		<Genre>댄스</Genre>
		<Released-date>2015</Released-date>
		<Song>
		<Name>피땀눈물</Name>
		<PlayTime>
		     <hours>1</hours>
		     <minutes>02</minutes>
			 <seconds>03</seconds>
		</PlayTime>
		</Song>	
	</Cd>
	<Mp3>
		<Title>BTD 2집</Title>
		<Artist>BTS</Artist>
		<Genre>댄스</Genre>
		<Released-date>2015</Released-date>
		<Song>
		<Name>고해</Name>
		<PlayTime>
		     <hours>1</hours>
		     <minutes>02</minutes>
			 <seconds>03</seconds>
		</PlayTime>
		</Song>
	</Mp3>
	<Record>
		<Title>BTD 3집</Title>
		<Artist>BTS</Artist>
		<Genre>댄스</Genre>
		<Released-date>2015</Released-date>
		<Song>
		<Name>cheer up!</Name>
		<PlayTime>
		     <hours>1</hours>
		     <minutes>02</minutes>
			 <seconds>03</seconds>
		</PlayTime>
		</Song>
	</Record>	

</AudioCatalog>